swagdogsrc/__init__.py
swagdogsrc/swagdog.py
swagdog-0.1.dist-info/METADATA
swagdog-0.1.dist-info/WHEEL
swagdog-0.1.dist-info/top_level.txt
swagdog-0.1.dist-info/zip-safe
swagdog-0.1.dist-info/RECORD
